numpy_pydantic_types/__init__.py
numpy_pydantic_types/__init__.pyi
numpy_pydantic_types/floats.py
numpy_pydantic_types/numpy_type.py
numpy_pydantic_types/requirements-dev.txt
numpy_pydantic_types/requirements.txt
numpy_pydantic_types-0.1.0a0.dist-info/LICENSE
numpy_pydantic_types-0.1.0a0.dist-info/METADATA
numpy_pydantic_types-0.1.0a0.dist-info/WHEEL
numpy_pydantic_types-0.1.0a0.dist-info/RECORD
