Metadata-Version: 2.1
Name: numpy_pydantic_types
Version: 0.1.0a0
Summary: numpy-pydantic-types is a Python library providing numpy scalar data types compatible with pydantic, allowing for easy validation and enforcement of numerical precision in pydantic models.
Home-page: https://github.com/eksavazquez/numpy-pydantic-types
License: MIT
Keywords: pydantic,numpy,typing,validation
Author: Álvaro Vázquez Ortiz
Author-email: alvvazort@gmail.com
Maintainer: Álvaro Vázquez Ortiz
Maintainer-email: alvvazort@gmail.com
Requires-Python: >=3.9,<3.13
Classifier: Development Status :: 5 - Production/Stable
Classifier: License :: OSI Approved :: MIT License
Classifier: Operating System :: OS Independent
Classifier: Programming Language :: Python :: 3
Classifier: Programming Language :: Python :: 3.9
Classifier: Programming Language :: Python :: 3.10
Classifier: Programming Language :: Python :: 3.11
Classifier: Programming Language :: Python :: 3.12
Classifier: Topic :: Software Development :: Libraries :: Python Modules
Requires-Dist: numpy (>=2.0.0)
Requires-Dist: pydantic (>=2.0,<3.0)
